st_audiorec/__init__.py
st_audiorec/frontend/.env
st_audiorec/frontend/.prettierrc
st_audiorec/frontend/package-lock.json
st_audiorec/frontend/package.json
st_audiorec/frontend/tsconfig.json
st_audiorec/frontend/build/asset-manifest.json
st_audiorec/frontend/build/bootstrap.min.css
st_audiorec/frontend/build/index.html
st_audiorec/frontend/build/precache-manifest.4829c060d313d0b0d13d9af3b0180289.js
st_audiorec/frontend/build/service-worker.js
st_audiorec/frontend/build/styles.css
st_audiorec/frontend/build/static/css/2.bfbf028b.chunk.css
st_audiorec/frontend/build/static/css/2.bfbf028b.chunk.css.map
st_audiorec/frontend/build/static/js/2.270b84d8.chunk.js
st_audiorec/frontend/build/static/js/2.270b84d8.chunk.js.LICENSE.txt
st_audiorec/frontend/build/static/js/2.270b84d8.chunk.js.map
st_audiorec/frontend/build/static/js/main.833ba252.chunk.js
st_audiorec/frontend/build/static/js/main.833ba252.chunk.js.map
st_audiorec/frontend/build/static/js/runtime-main.11ec9aca.js
st_audiorec/frontend/build/static/js/runtime-main.11ec9aca.js.map
st_audiorec/frontend/public/bootstrap.min.css
st_audiorec/frontend/public/index.html
st_audiorec/frontend/public/styles.css
st_audiorec/frontend/src/StreamlitAudioRecorder.tsx
st_audiorec/frontend/src/index.tsx
st_audiorec/frontend/src/react-app-env.d.ts
streamlit_audiorec-0.1.3.dist-info/LICENCE
streamlit_audiorec-0.1.3.dist-info/METADATA
streamlit_audiorec-0.1.3.dist-info/WHEEL
streamlit_audiorec-0.1.3.dist-info/top_level.txt
streamlit_audiorec-0.1.3.dist-info/RECORD
