Metadata-Version: 2.1
Name: streamlit-audiorec
Version: 0.1.3
Summary: Record audio from the user's microphone in apps that are deployed to the web. (via Browser Media-API) [GitHub ☆ 160+: steamlit-audio-recorder]
Home-page: https://github.com/stefanrmmr/streamlit-audio-recorder
Author: Stefan Rummer
Author-email: 
License: UNKNOWN
Platform: UNKNOWN
Requires-Python: >=3.7
License-File: LICENCE
